{
    "books": [
      { "id": 1, "title": "The River and the Source", "author": "Margaret Ogola", "status": "Read", "image": "https://upload.wikimedia.org/wikipedia/en/9/99/The_River_and_the_Source_cover.jpg" },
      { "id": 2, "title": "Petals of Blood", "author": "Ngũgĩ wa Thiong'o", "status": "Unread", "image": "https://upload.wikimedia.org/wikipedia/en/2/2a/Petals_of_Blood.jpg" },
      { "id": 3, "title": "Weep Not, Child", "author": "Ngũgĩ wa Thiong'o", "status": "Reading", "image": "https://upload.wikimedia.org/wikipedia/en/6/6b/Weep_Not%2C_Child.jpg" },
      { "id": 4, "title": "Dust", "author": "Yvonne Adhiambo Owuor", "status": "Read", "image": "https://images-na.ssl-images-amazon.com/images/S/compressed.photo.goodreads.com/books/1378933062l/18085436.jpg" },
      { "id": 5, "title": "So Long a Letter", "author": "Mariama Bâ", "status": "Unread", "image": "https://images-na.ssl-images-amazon.com/images/S/compressed.photo.goodreads.com/books/1442875242l/849259.jpg" },
      { "id": 6, "title": "Blackass", "author": "A. Igoni Barrett", "status": "Reading", "image": "https://images-na.ssl-images-amazon.com/images/S/compressed.photo.goodreads.com/books/1439392675l/23492615.jpg" },
      { "id": 7, "title": "Born a Crime", "author": "Trevor Noah", "status": "Read", "image": "https://images-na.ssl-images-amazon.com/images/S/compressed.photo.goodreads.com/books/1476284003l/29780253.jpg" },
      { "id": 8, "title": "Americanah", "author": "Chimamanda Ngozi Adichie", "status": "Unread", "image": "https://images-na.ssl-images-amazon.com/images/S/compressed.photo.goodreads.com/books/1356655682l/15796700.jpg" },
      { "id": 9, "title": "Efuru", "author": "Flora Nwapa", "status": "Read", "image": "https://images-na.ssl-images-amazon.com/images/S/compressed.photo.goodreads.com/books/1349061166l/2187466.jpg" },
      { "id": 10, "title": "The Shadow of Imana", "author": "Veronique Tadjo", "status": "Unread", "image": "https://images-na.ssl-images-amazon.com/images/S/compressed.photo.goodreads.com/books/1328084424l/370310.jpg" }
    ]
  }
  